lsidentity/__init__.py
lsidentity/contexts/__init__.py
lsidentity-1.0.2.dist-info/METADATA
lsidentity-1.0.2.dist-info/WHEEL
lsidentity-1.0.2.dist-info/entry_points.txt
lsidentity-1.0.2.dist-info/RECORD
